minaki_cli/__init__.py
minaki_cli/api.py
minaki_cli/cli.py
minaki_cli/config.py
minaki_cli/wg_control.py
minaki_vpn-0.1.1.dist-info/licenses/LICENSE.txt
minaki_vpn-0.1.1.dist-info/METADATA
minaki_vpn-0.1.1.dist-info/WHEEL
minaki_vpn-0.1.1.dist-info/entry_points.txt
minaki_vpn-0.1.1.dist-info/top_level.txt
minaki_vpn-0.1.1.dist-info/RECORD
