Metadata-Version: 2.4
Name: minaki-vpn
Version: 0.1.1
Summary: MinakiLabs CLI for managing WireGuard VPN tunnels - fixed sub-domains
Author-email: Andrew Polykandriotis <support@minakilabs.com>
License: MIT
Project-URL: Homepage, https://minaki.io
Project-URL: Repository, https://github.com/minakilabs/minaki-vpn
Keywords: vpn,cli,wireguard,minaki,tunnel
License-File: LICENSE.txt
Requires-Dist: click
Requires-Dist: requests
Requires-Dist: rich
Dynamic: license-file
